gargparse.py
gargparse-0.0.6.dist-info/DESCRIPTION.rst
gargparse-0.0.6.dist-info/METADATA
gargparse-0.0.6.dist-info/RECORD
gargparse-0.0.6.dist-info/WHEEL
gargparse-0.0.6.dist-info/metadata.json
gargparse-0.0.6.dist-info/top_level.txt
